queueing_systems/__init__.py
queueing_systems/functions.py
queueing_systems-0.1.2.dist-info/LICENSE
queueing_systems-0.1.2.dist-info/METADATA
queueing_systems-0.1.2.dist-info/WHEEL
queueing_systems-0.1.2.dist-info/top_level.txt
queueing_systems-0.1.2.dist-info/RECORD
