Metadata-Version: 2.1
Name: queueing-systems
Version: 0.1.2
Summary: Python package for queueing system parameter estimation using queueing theory
Home-page: https://github.com/pauterv/queueing_systems
Author: Paulius Tervydis
Author-email: Paulius.Tervydis@ktu.lt
Classifier: Development Status :: 3 - Alpha
Classifier: License :: OSI Approved :: MIT License
Classifier: Programming Language :: Python :: 3
Classifier: Programming Language :: Python :: 3.6
Classifier: Programming Language :: Python :: 3.7
Classifier: Programming Language :: Python :: 3.8
License-File: LICENSE
Requires-Dist: numpy
Requires-Dist: pandas
Requires-Dist: matplotlib
